repoze.workflow-1.1-py3.8-nspkg.pth
repoze/workflow/__init__.py
repoze/workflow/_compat.py
repoze/workflow/interfaces.py
repoze/workflow/meta.zcml
repoze/workflow/statemachine.py
repoze/workflow/testing.py
repoze/workflow/workflow.py
repoze/workflow/zcml.py
repoze/workflow/tests/__init__.py
repoze/workflow/tests/test_statemachine.py
repoze/workflow/tests/test_testing.py
repoze/workflow/tests/test_workflow.py
repoze/workflow/tests/test_zcml.py
repoze/workflow/tests/fixtures/__init__.py
repoze/workflow/tests/fixtures/configure.zcml
repoze/workflow/tests/fixtures/dummy.py
repoze.workflow-1.1.dist-info/LICENSE.txt
repoze.workflow-1.1.dist-info/METADATA
repoze.workflow-1.1.dist-info/WHEEL
repoze.workflow-1.1.dist-info/entry_points.txt
repoze.workflow-1.1.dist-info/namespace_packages.txt
repoze.workflow-1.1.dist-info/top_level.txt
repoze.workflow-1.1.dist-info/RECORD
